impectPy/__init__.py
impectPy/access_token.py
impectPy/config.py
impectPy/events.py
impectPy/formations.py
impectPy/generate_xml.py
impectPy/helpers.py
impectPy/impect.py
impectPy/iterations.py
impectPy/matches.py
impectPy/player_iteration_averages.py
impectPy/player_iteration_scores.py
impectPy/player_match_scores.py
impectPy/player_matchsums.py
impectPy/player_profile_scores.py
impectPy/set_pieces.py
impectPy/squad_coefficients.py
impectPy/squad_iteration_averages.py
impectPy/squad_iteration_scores.py
impectPy/squad_match_scores.py
impectPy/squad_matchsums.py
impectPy/squad_ratings.py
impectPy/starting_positions.py
impectPy/substitutions.py
impectpy-2.5.5.dist-info/licenses/LICENSE.md
impectpy-2.5.5.dist-info/METADATA
impectpy-2.5.5.dist-info/WHEEL
impectpy-2.5.5.dist-info/top_level.txt
impectpy-2.5.5.dist-info/RECORD
