Metadata-Version: 2.4
Name: impectPy
Version: 2.5.5
Summary: A Python package to facilitate interaction with the Impect customer API
Home-page: https://github.com/ImpectAPI/impectPy
Author: Impect
Author-email: info@impect.com
License: MIT
License-File: LICENSE.md
Requires-Dist: requests>=2.24.0
Requires-Dist: pandas>=2.2.0
Requires-Dist: numpy>=1.24.2
Dynamic: author
Dynamic: author-email
Dynamic: description
Dynamic: description-content-type
Dynamic: home-page
Dynamic: license
Dynamic: license-file
Dynamic: requires-dist
Dynamic: summary
